ads2gephi/__init__.py
ads2gephi/ads2gephi.py
ads2gephi/cli.py
ads2gephi-0.3.8.dist-info/entry_points.txt
ads2gephi-0.3.8.dist-info/LICENSE.txt
ads2gephi-0.3.8.dist-info/WHEEL
ads2gephi-0.3.8.dist-info/METADATA
ads2gephi-0.3.8.dist-info/RECORD
