Metadata-Version: 2.1
Name: ads2gephi
Version: 0.3.8
Summary: A command line tool for querying and modeling citation networks from the Astrophysical Data System (ADS) in a format compatible with Gephi
Home-page: https://github.com/03b8/ads2gephi
License: MIT
Keywords: citation network,network analysis,astrophysical data system
Author: Theo Costea
Author-email: theo.costea@gmail.com
Requires-Python: >=3.5
Classifier: License :: OSI Approved :: MIT License
Classifier: Programming Language :: Python :: 3
Classifier: Programming Language :: Python :: 3.5
Classifier: Programming Language :: Python :: 3.6
Classifier: Programming Language :: Python :: 3.7
Classifier: Programming Language :: Python :: 3.8
Classifier: Programming Language :: Python :: 3.9
Requires-Dist: ads (>=0.12.3,<0.13.0)
Requires-Dist: click (>=7.0,<8.0)
Requires-Dist: configparser (>=3.7,<4.0)
Requires-Dist: python-igraph (>=0.8.2,<0.9.0)
Requires-Dist: sqlalchemy (>=1.3,<2.0)
Requires-Dist: tqdm (>=4.32,<5.0)
Requires-Dist: yaspin (>=0.14.3,<0.15.0)
Project-URL: Repository, https://github.com/03b8/ads2gephi
